Basic Verilog/mux.v
module mux(
input A,
input B,
input S,
output Y
);
assign Y= (~S&A)|(S&B);

endmodule

mux_tb.v
module mux_tb;
reg A;
reg B;
reg S;
wire Y;

mux uut(
  .A(A),
  .B(B),
  .S(S),
  .Y(Y)
);
initial begin
    $dumpfile("mux.vcd");
    $dumpvars(0 ,mux_tb);
    $monitor("A=%b B=%b S=%b Y=%b", A,B,S,Y);
    A=0; B=0; S=0;
    #10;
    A=0; B=0; S=1;
    #10;
    A=0; B=1; S=0;
    #10;
    A=0; B=1; S=1;
    #10;
    A=1; B=0; S=0;
    #10;
    A=1; B=0; S=1;
    #10;
    A=1; B=1; S=0;
    #10;
    A=1; B=1; S=1;
    #10;
    $finish;
end 
endmodule

mux.vcd
$date
	Wed Sep  9 22:39:12 2026
$end
$version
	Icarus Verilog
$end
$timescale
	1s
$end
$scope module mux_tb $end
$var wire 1 ! Y $end
$var reg 1 " A $end
$var reg 1 # B $end
$var reg 1 $ S $end
$scope module uut $end
$var wire 1 " A $end
$var wire 1 # B $end
$var wire 1 $ S $end
$var wire 1 ! Y $end
$upscope $end
$upscope $end
$enddefinitions $end
$comment Show the parameter values. $end
$dumpall
$end
#0
$dumpvars
0$
0#
0"
0!
$end
#10
1$
#20
0$
1#
#30
1!
1$
#40
1!
0$
0#
1"
#50
0!
1$
#60
1!
0$
1#
#70
1$
